Srpc/__init__.py
Srpc/external_access_ui_client.py
Srpc/installer_client.py
Srpc/instrument_client.py
Srpc/mdl_stage_ui_client.py
Srpc/remote_installer.py
Srpc/server.py
Srpc/service.py
Srpc/TemScripting/__init__.py
Srpc/TemScripting/detector.py
Srpc/TemScripting/instrument.py
Srpc/TemScripting/instrument_mock.py
Srpc/apps/__init__.py
Srpc/apps/external_access.py
Srpc/apps/mdl_stage_ui.py
TemServer/__init__.py
apollo/__init__.py
apollo/application.py
common/__init__.py
common/environment.py
common/file_utils.py
common/git.py
common/process.py
common/singleton.py
common/squish_info.py
common/video_metadata.py
common/wildcard.py
external_access_ui/__init__.py
installer/__init__.py
mdl_stage_ui/__init__.py
tests/__init__.py
tests/test_execution_info.py
tests/test_file_utils.py
tests/test_git.py
tests/test_process.py
utils/__init__.py
utils/elasticsearch_utils.py
utils/enum_helper.py
utils/helper.py
utils/image_helper.py
utils/mathematical_tools.py
utils/menu.py
utils/performance_utilities.py
utils/screen_capture.py
utils/sqllite.py
utils/string_utils.py
utils/test_utilities.py
utils/tooltip_helper.py
utils/window.py
utils/windows_taskbar.py
velox/__init__.py
velox/application.py
velox/configuration.py
velox/current_stem_configuration_helper.py
velox/detector_rotation_helper.py
velox/experiment.py
velox/helper.py
velox/launcher.py
velox/prepare_acquisition_state_helper.py
velox/registry_utils.py
velox/velox_log_reader.py
velox/velox_performance_log_reader.py
velox/widget_image_grabber.py
velox/widget_image_series_grabber.py
velox/window_layout_helper.py
velframepkg-0.0.1.dist-info/METADATA
velframepkg-0.0.1.dist-info/WHEEL
velframepkg-0.0.1.dist-info/top_level.txt
velframepkg-0.0.1.dist-info/RECORD
